Metadata-Version: 2.1
Name: fabio-libpypro
Version: 0.1
Summary: Modulo para exemplificar construcao de projetos Python no curso Pytools
Home-page: https://github.com/fabio1008/libpythonpro
Author: Fabio Luis
Author-email: fabiocarini2003@gmail.com
License:                     GNU AFFERO GENERAL PUBLIC LICENSE
Platform: UNKNOWN
Classifier: Development Status :: 2 - Pre-Alpha
Classifier: Environment :: Console
Classifier: Intended Audience :: Developers
Classifier: License :: OSI Approved :: GNU Affero General Public License v3 or later (AGPLv3+)
Classifier: Operating System :: OS Independent
Classifier: Programming Language :: Python
Classifier: Programming Language :: Python :: 3.9
Classifier: Framework :: Pytest
License-File: LICENSE
